tortoise/__init__.py
tortoise/backends/__init__.py
tortoise/backends/asyncpg/__init__.py
tortoise/backends/asyncpg/client.py
tortoise/backends/asyncpg/executor.py
tortoise/backends/asyncpg/schema_generator.py
tortoise/backends/base/__init__.py
tortoise/backends/base/client.py
tortoise/backends/base/config_generator.py
tortoise/backends/base/executor.py
tortoise/backends/base/schema_generator.py
tortoise/backends/base_postgres/__init__.py
tortoise/backends/base_postgres/client.py
tortoise/backends/base_postgres/executor.py
tortoise/backends/base_postgres/schema_generator.py
tortoise/backends/mssql/__init__.py
tortoise/backends/mssql/client.py
tortoise/backends/mssql/executor.py
tortoise/backends/mssql/schema_generator.py
tortoise/backends/mysql/__init__.py
tortoise/backends/mysql/client.py
tortoise/backends/mysql/executor.py
tortoise/backends/mysql/schema_generator.py
tortoise/backends/odbc/__init__.py
tortoise/backends/odbc/client.py
tortoise/backends/odbc/executor.py
tortoise/backends/oracle/__init__.py
tortoise/backends/oracle/client.py
tortoise/backends/oracle/executor.py
tortoise/backends/oracle/schema_generator.py
tortoise/backends/psycopg/__init__.py
tortoise/backends/psycopg/client.py
tortoise/backends/psycopg/executor.py
tortoise/backends/psycopg/schema_generator.py
tortoise/backends/sqlcipher/__init__.py
tortoise/backends/sqlcipher/client.py
tortoise/backends/sqlcipher/executor.py
tortoise/backends/sqlcipher/schema_generator.py
tortoise/backends/sqlite/__init__.py
tortoise/backends/sqlite/client.py
tortoise/backends/sqlite/executor.py
tortoise/backends/sqlite/schema_generator.py
tortoise/connection.py
tortoise/contrib/__init__.py
tortoise/contrib/aiohttp/__init__.py
tortoise/contrib/blacksheep/__init__.py
tortoise/contrib/fastapi/__init__.py
tortoise/contrib/mysql/__init__.py
tortoise/contrib/mysql/fields.py
tortoise/contrib/mysql/functions.py
tortoise/contrib/mysql/indexes.py
tortoise/contrib/mysql/json_functions.py
tortoise/contrib/mysql/search.py
tortoise_plus-0.25.1.dist-info/LICENSE.txt
tortoise_plus-0.25.1.dist-info/METADATA
tortoise_plus-0.25.1.dist-info/WHEEL
tortoise_plus-0.25.1.dist-info/RECORD
