Metadata-Version: 2.3
Name: tortoise-plus
Version: 0.25.1
Summary: add sqlcipher support
License: Apache-2.0
Keywords: sql,mysql,postgres,psql,sqlite,aiosqlite,asyncpg,relational,database,rdbms,orm,object mapper,async,asyncio,aio,psycopg
Author: tianqing
Author-email: tianqing108@126.com
Requires-Python: >=3.9
Classifier: Development Status :: 3 - Alpha
Classifier: Framework :: AsyncIO
Classifier: Intended Audience :: Developers
Classifier: License :: OSI Approved :: Apache Software License
Classifier: Operating System :: MacOS :: MacOS X
Classifier: Operating System :: Microsoft :: Windows
Classifier: Operating System :: POSIX
Classifier: Programming Language :: PL/SQL
Classifier: Programming Language :: Python :: 3
Classifier: Programming Language :: Python :: 3.9
Classifier: Programming Language :: Python :: 3.10
Classifier: Programming Language :: Python :: 3.11
Classifier: Programming Language :: Python :: 3.12
Classifier: Programming Language :: Python :: 3.13
Classifier: Programming Language :: Python :: Implementation :: CPython
Classifier: Programming Language :: Python :: Implementation :: PyPy
Classifier: Topic :: Database
Classifier: Topic :: Software Development :: Libraries :: Python Modules
Provides-Extra: accel
Provides-Extra: aiomysql
Provides-Extra: aiosqlcipher
Provides-Extra: asyncmy
Provides-Extra: asyncodbc
Provides-Extra: asyncpg
Provides-Extra: psycopg
Requires-Dist: aiomysql ; extra == "aiomysql"
Requires-Dist: aiosqlcipher ; extra == "aiosqlcipher"
Requires-Dist: aiosqlite (>=0.16.0,<1.0.0)
Requires-Dist: asyncmy (>=0.2.8,<1.0.0) ; (python_version < "4.0") and (extra == "asyncmy")
Requires-Dist: asyncodbc (>=0.1.1,<1.0.0) ; (python_version < "4.0") and (extra == "asyncodbc")
Requires-Dist: asyncpg ; extra == "asyncpg"
Requires-Dist: ciso8601 ; (sys_platform != "win32" and implementation_name == "cpython") and (extra == "accel")
Requires-Dist: iso8601 (>=2.1.0,<3.0.0) ; python_version < "4.0"
Requires-Dist: orjson ; extra == "accel"
Requires-Dist: psycopg[binary,pool] (>=3.0.12,<4.0.0) ; extra == "psycopg"
Requires-Dist: pypika-tortoise (>=0.6.1,<1.0.0)
Requires-Dist: pytz
Requires-Dist: uvloop ; (sys_platform != "win32" and implementation_name == "cpython") and (extra == "accel")
Project-URL: Documentation, https://tortoise-orm.readthedocs.io
Project-URL: Homepage, https://github.com/tortoise/tortoise-orm
Project-URL: Repository, https://github.com/tortoise/tortoise-orm.git
